topsis_cin/__init__.py
topsis_cin/decision.py
topsis_cin/main.py
topsis_cin-0.1.1.dist-info/LICENCE
topsis_cin-0.1.1.dist-info/METADATA
topsis_cin-0.1.1.dist-info/WHEEL
topsis_cin-0.1.1.dist-info/RECORD
