Metadata-Version: 2.3
Name: topsis_cin
Version: 0.1.1
Summary: Biblioteca Topsis
License: MIT
Author: Lucas Luís, Mateus da Silva
Requires-Python: >=3.10
Classifier: License :: OSI Approved :: MIT License
Classifier: Programming Language :: Python :: 3
Classifier: Programming Language :: Python :: 3.10
Classifier: Programming Language :: Python :: 3.11
Classifier: Programming Language :: Python :: 3.12
Classifier: Programming Language :: Python :: 3.13
Requires-Dist: numpy (==1.26.4)
